{
    "modules": [
        {
            "config": {
                "position": [
                    222,
                    592
                ]
            },
            "name": "New Model Object",
            "value": {
                "actionGroup": {
                    "_default0_list": false,
                    "_default1_show": false,
                    "_default2_new_create": false,
                    "_default3_edit_update": false,
                    "_default4_delete": false,
                    "customActions": []
                },
                "name": "News",
                "objectsettings": {
                    "addDeletedField": true,
                    "addHiddenField": true,
                    "addStarttimeEndtimeFields": true,
                    "aggregateRoot": false,
                    "categorizable": false,
                    "description": "",
                    "mapToTable": "",
                    "parentClass": "\\GeorgRinger\\News\\Domain\\Model\\News",
                    "sorting": false,
                    "type": "Entity",
                    "uid": "884170794198"
                },
                "propertyGroup": {
                    "properties": [
                        {
                            "allowedFileTypes": "",
                            "maxItems": "1",
                            "propertyDescription": "",
                            "propertyIsExcludeField": false,
                            "propertyIsRequired": true,
                            "propertyName": "date",
                            "propertyType": "Integer",
                            "uid": "234793258963"
                        },
                        {
                            "allowedFileTypes": "",
                            "maxItems": "1",
                            "propertyDescription": "",
                            "propertyIsExcludeField": false,
                            "propertyIsRequired": true,
                            "propertyName": "subtitle",
                            "propertyType": "String",
                            "uid": "1271669897762"
                        },
                        {
                            "allowedFileTypes": "",
                            "maxItems": "1",
                            "propertyDescription": "",
                            "propertyIsExcludeField": false,
                            "propertyIsRequired": false,
                            "propertyName": "isbn",
                            "propertyType": "String",
                            "uid": "1090939879668"
                        },
                        {
                            "allowedFileTypes": "",
                            "maxItems": "1",
                            "propertyDescription": "",
                            "propertyIsExcludeField": false,
                            "propertyIsRequired": false,
                            "propertyName": "issn",
                            "propertyType": "String",
                            "uid": "1127423230792"
                        },
                        {
                            "allowedFileTypes": "",
                            "maxItems": "1",
                            "propertyDescription": "",
                            "propertyIsExcludeField": false,
                            "propertyIsRequired": false,
                            "propertyName": "edition",
                            "propertyType": "String",
                            "uid": "846665224098"
                        },
                        {
                            "allowedFileTypes": "",
                            "maxItems": "1",
                            "propertyDescription": "",
                            "propertyIsExcludeField": false,
                            "propertyIsRequired": true,
                            "propertyName": "yearofpublicaition",
                            "propertyType": "Integer",
                            "uid": "465384024262"
                        },
                        {
                            "allowedFileTypes": "",
                            "maxItems": "1",
                            "propertyDescription": "",
                            "propertyIsExcludeField": false,
                            "propertyIsRequired": false,
                            "propertyName": "channels",
                            "propertyType": "Integer",
                            "uid": "357808531881"
                        },
                        {
                            "allowedFileTypes": "",
                            "maxItems": "1",
                            "propertyDescription": "",
                            "propertyIsExcludeField": false,
                            "propertyIsRequired": true,
                            "propertyName": "news",
                            "propertyType": "Integer",
                            "uid": "306433942975"
                        },
                        {
                            "allowedFileTypes": "",
                            "maxItems": "1",
                            "propertyDescription": "",
                            "propertyIsExcludeField": false,
                            "propertyIsRequired": false,
                            "propertyName": "keywords",
                            "propertyType": "Text",
                            "uid": "285651633981"
                        },
                        {
                            "allowedFileTypes": "",
                            "maxItems": "1",
                            "propertyDescription": "",
                            "propertyIsExcludeField": false,
                            "propertyIsRequired": true,
                            "propertyName": "hrsg",
                            "propertyType": "Boolean",
                            "uid": "186163003313"
                        }
                    ]
                },
                "relationGroup": {
                    "relations": [
                        {
                            "foreignRelationClass": "",
                            "lazyLoading": true,
                            "propertyIsExcludeField": false,
                            "relationDescription": "",
                            "relationName": "idAuthor",
                            "relationType": "manyToMany",
                            "relationWire": "[wired]",
                            "uid": "432031968945"
                        },
                        {
                            "foreignRelationClass": "",
                            "lazyLoading": true,
                            "propertyIsExcludeField": true,
                            "relationDescription": "",
                            "relationName": "idPublisher",
                            "relationType": "manyToMany",
                            "relationWire": "[wired]",
                            "uid": "393915008928"
                        },
                        {
                            "foreignRelationClass": "",
                            "lazyLoading": true,
                            "propertyIsExcludeField": true,
                            "relationDescription": "",
                            "relationName": "idCanton",
                            "relationType": "manyToMany",
                            "relationWire": "[wired]",
                            "uid": "934677918302"
                        },
                        {
                            "foreignRelationClass": "",
                            "lazyLoading": true,
                            "propertyIsExcludeField": true,
                            "relationDescription": "",
                            "relationName": "idAdresse",
                            "relationType": "manyToMany",
                            "relationWire": "[wired]",
                            "uid": "1367924202115"
                        },
                        {
                            "foreignRelationClass": "",
                            "lazyLoading": false,
                            "propertyIsExcludeField": true,
                            "relationDescription": "",
                            "relationName": "idInformationstype",
                            "relationType": "zeroToMany",
                            "relationWire": "[wired]",
                            "uid": "308477501729"
                        },
                        {
                            "foreignRelationClass": "",
                            "lazyLoading": false,
                            "propertyIsExcludeField": true,
                            "relationDescription": "",
                            "relationName": "idCategory",
                            "relationType": "manyToOne",
                            "relationWire": "[wired]",
                            "uid": "1414041246328"
                        }
                    ]
                }
            }
        },
        {
            "config": {
                "position": [
                    645,
                    610
                ]
            },
            "name": "New Model Object",
            "value": {
                "actionGroup": {
                    "_default0_list": false,
                    "_default1_show": false,
                    "_default2_new_create": false,
                    "_default3_edit_update": false,
                    "_default4_delete": false,
                    "customActions": []
                },
                "name": "Adresse",
                "objectsettings": {
                    "addDeletedField": true,
                    "addHiddenField": true,
                    "addStarttimeEndtimeFields": false,
                    "aggregateRoot": false,
                    "categorizable": false,
                    "description": "",
                    "mapToTable": "",
                    "parentClass": "",
                    "sorting": true,
                    "type": "Entity",
                    "uid": "167147602477"
                },
                "propertyGroup": {
                    "properties": [
                        {
                            "allowedFileTypes": "",
                            "maxItems": "1",
                            "propertyDescription": "",
                            "propertyIsExcludeField": true,
                            "propertyIsRequired": false,
                            "propertyName": "institution",
                            "propertyType": "String",
                            "uid": "438542610126"
                        },
                        {
                            "allowedFileTypes": "",
                            "maxItems": "1",
                            "propertyDescription": "",
                            "propertyIsExcludeField": true,
                            "propertyIsRequired": true,
                            "propertyName": "category",
                            "propertyType": "Integer",
                            "uid": "956553315213"
                        },
                        {
                            "allowedFileTypes": "",
                            "maxItems": "1",
                            "propertyDescription": "",
                            "propertyIsExcludeField": true,
                            "propertyIsRequired": false,
                            "propertyName": "department",
                            "propertyType": "String",
                            "uid": "895297752591"
                        },
                        {
                            "allowedFileTypes": "",
                            "maxItems": "1",
                            "propertyDescription": "",
                            "propertyIsExcludeField": true,
                            "propertyIsRequired": false,
                            "propertyName": "short",
                            "propertyType": "String",
                            "uid": "1080242530337"
                        },
                        {
                            "allowedFileTypes": "",
                            "maxItems": "1",
                            "propertyDescription": "",
                            "propertyIsExcludeField": true,
                            "propertyIsRequired": false,
                            "propertyName": "displayname",
                            "propertyType": "String",
                            "uid": "328159802029"
                        },
                        {
                            "allowedFileTypes": "",
                            "maxItems": "1",
                            "propertyDescription": "",
                            "propertyIsExcludeField": true,
                            "propertyIsRequired": false,
                            "propertyName": "addition",
                            "propertyType": "String",
                            "uid": "868001361436"
                        },
                        {
                            "allowedFileTypes": "",
                            "maxItems": "1",
                            "propertyDescription": "",
                            "propertyIsExcludeField": true,
                            "propertyIsRequired": false,
                            "propertyName": "adresse",
                            "propertyType": "String",
                            "uid": "990266813151"
                        },
                        {
                            "allowedFileTypes": "",
                            "maxItems": "1",
                            "propertyDescription": "",
                            "propertyIsExcludeField": true,
                            "propertyIsRequired": false,
                            "propertyName": "postOffice",
                            "propertyType": "String",
                            "uid": "1015790204378"
                        },
                        {
                            "allowedFileTypes": "",
                            "maxItems": "1",
                            "propertyDescription": "",
                            "propertyIsExcludeField": true,
                            "propertyIsRequired": false,
                            "propertyName": "postcode",
                            "propertyType": "String",
                            "uid": "953054704010"
                        },
                        {
                            "allowedFileTypes": "",
                            "maxItems": "1",
                            "propertyDescription": "",
                            "propertyIsExcludeField": true,
                            "propertyIsRequired": false,
                            "propertyName": "location",
                            "propertyType": "String",
                            "uid": "374384710001"
                        },
                        {
                            "allowedFileTypes": "",
                            "maxItems": "1",
                            "propertyDescription": "",
                            "propertyIsExcludeField": true,
                            "propertyIsRequired": false,
                            "propertyName": "pPostcode",
                            "propertyType": "String",
                            "uid": "1075428023836"
                        },
                        {
                            "allowedFileTypes": "",
                            "maxItems": "1",
                            "propertyDescription": "",
                            "propertyIsExcludeField": true,
                            "propertyIsRequired": false,
                            "propertyName": "pLocation",
                            "propertyType": "String",
                            "uid": "620031738629"
                        },
                        {
                            "allowedFileTypes": "",
                            "maxItems": "1",
                            "propertyDescription": "",
                            "propertyIsExcludeField": true,
                            "propertyIsRequired": true,
                            "propertyName": "areasOfWork",
                            "propertyType": "Integer",
                            "uid": "1024602528749"
                        },
                        {
                            "allowedFileTypes": "",
                            "maxItems": "1",
                            "propertyDescription": "",
                            "propertyIsExcludeField": true,
                            "propertyIsRequired": true,
                            "propertyName": "canton",
                            "propertyType": "String",
                            "uid": "89265174858"
                        },
                        {
                            "allowedFileTypes": "",
                            "maxItems": "1",
                            "propertyDescription": "",
                            "propertyIsExcludeField": true,
                            "propertyIsRequired": false,
                            "propertyName": "phone",
                            "propertyType": "String",
                            "uid": "1323045200678"
                        },
                        {
                            "allowedFileTypes": "",
                            "maxItems": "1",
                            "propertyDescription": "",
                            "propertyIsExcludeField": true,
                            "propertyIsRequired": false,
                            "propertyName": "telefax",
                            "propertyType": "String",
                            "uid": "645543839170"
                        },
                        {
                            "allowedFileTypes": "",
                            "maxItems": "1",
                            "propertyDescription": "",
                            "propertyIsExcludeField": true,
                            "propertyIsRequired": false,
                            "propertyName": "email",
                            "propertyType": "String",
                            "uid": "480393148270"
                        },
                        {
                            "allowedFileTypes": "",
                            "maxItems": "1",
                            "propertyDescription": "",
                            "propertyIsExcludeField": true,
                            "propertyIsRequired": false,
                            "propertyName": "www",
                            "propertyType": "String",
                            "uid": "961995542973"
                        },
                        {
                            "allowedFileTypes": "",
                            "maxItems": "1",
                            "propertyDescription": "",
                            "propertyIsExcludeField": true,
                            "propertyIsRequired": false,
                            "propertyName": "remark",
                            "propertyType": "String",
                            "uid": "440224536285"
                        },
                        {
                            "allowedFileTypes": "",
                            "maxItems": "1",
                            "propertyDescription": "",
                            "propertyIsExcludeField": true,
                            "propertyIsRequired": false,
                            "propertyName": "other",
                            "propertyType": "String",
                            "uid": "961439679757"
                        },
                        {
                            "allowedFileTypes": "",
                            "maxItems": "1",
                            "propertyDescription": "",
                            "propertyIsExcludeField": true,
                            "propertyIsRequired": true,
                            "propertyName": "datasheet",
                            "propertyType": "Integer",
                            "uid": "1244457121895"
                        },
                        {
                            "allowedFileTypes": "",
                            "maxItems": "1",
                            "propertyDescription": "",
                            "propertyIsExcludeField": true,
                            "propertyIsRequired": true,
                            "propertyName": "backEmpty",
                            "propertyType": "Integer",
                            "uid": "226752025069"
                        },
                        {
                            "allowedFileTypes": "",
                            "maxItems": "1",
                            "propertyDescription": "",
                            "propertyIsExcludeField": true,
                            "propertyIsRequired": false,
                            "propertyName": "institutionShort",
                            "propertyType": "String",
                            "uid": "1267317921090"
                        },
                        {
                            "allowedFileTypes": "",
                            "maxItems": "1",
                            "propertyDescription": "",
                            "propertyIsExcludeField": true,
                            "propertyIsRequired": false,
                            "propertyName": "facebook",
                            "propertyType": "String",
                            "uid": "5728988393"
                        },
                        {
                            "allowedFileTypes": "",
                            "maxItems": "1",
                            "propertyDescription": "",
                            "propertyIsExcludeField": true,
                            "propertyIsRequired": false,
                            "propertyName": "twitter",
                            "propertyType": "String",
                            "uid": "319527815772"
                        },
                        {
                            "allowedFileTypes": "",
                            "maxItems": "1",
                            "propertyDescription": "other Social Media",
                            "propertyIsExcludeField": true,
                            "propertyIsRequired": false,
                            "propertyName": "otherSM",
                            "propertyType": "String",
                            "uid": "143901107851"
                        },
                        {
                            "allowedFileTypes": "",
                            "maxItems": "1",
                            "propertyDescription": "",
                            "propertyIsExcludeField": true,
                            "propertyIsRequired": false,
                            "propertyName": "googleplus",
                            "propertyType": "String",
                            "uid": "709753725386"
                        },
                        {
                            "allowedFileTypes": "",
                            "maxItems": "1",
                            "propertyDescription": "",
                            "propertyIsExcludeField": true,
                            "propertyIsRequired": false,
                            "propertyName": "xing",
                            "propertyType": "String",
                            "uid": "970498704536"
                        },
                        {
                            "allowedFileTypes": "",
                            "maxItems": "1",
                            "propertyDescription": "",
                            "propertyIsExcludeField": true,
                            "propertyIsRequired": false,
                            "propertyName": "youtube",
                            "propertyType": "String",
                            "uid": "1438788537509"
                        },
                        {
                            "allowedFileTypes": "",
                            "maxItems": "1",
                            "propertyDescription": "",
                            "propertyIsExcludeField": true,
                            "propertyIsRequired": false,
                            "propertyName": "rss",
                            "propertyType": "String",
                            "uid": "533897165684"
                        }
                    ]
                },
                "relationGroup": {
                    "relations": [
                        {
                            "foreignRelationClass": "",
                            "lazyLoading": false,
                            "propertyIsExcludeField": true,
                            "relationDescription": "",
                            "relationName": "idUser",
                            "relationType": "manyToOne",
                            "relationWire": "[wired]",
                            "uid": "574745817357"
                        },
                        {
                            "foreignRelationClass": "",
                            "lazyLoading": false,
                            "propertyIsExcludeField": true,
                            "relationDescription": "",
                            "relationName": "idCanton",
                            "relationType": "manyToOne",
                            "relationWire": "[wired]",
                            "uid": "837849782902"
                        },
                        {
                            "foreignRelationClass": "",
                            "lazyLoading": true,
                            "propertyIsExcludeField": true,
                            "relationDescription": "",
                            "relationName": "idAreaofwork",
                            "relationType": "manyToMany",
                            "relationWire": "[wired]",
                            "uid": "1044861095050"
                        },
                        {
                            "foreignRelationClass": "",
                            "lazyLoading": true,
                            "propertyIsExcludeField": true,
                            "relationDescription": "",
                            "relationName": "idEducation",
                            "relationType": "manyToMany",
                            "relationWire": "[wired]",
                            "uid": "657861267026"
                        }
                    ]
                }
            }
        },
        {
            "config": {
                "position": [
                    528,
                    23
                ]
            },
            "name": "New Model Object",
            "value": {
                "actionGroup": {
                    "_default0_list": false,
                    "_default1_show": false,
                    "_default2_new_create": false,
                    "_default3_edit_update": false,
                    "_default4_delete": false,
                    "customActions": []
                },
                "name": "Authors",
                "objectsettings": {
                    "addDeletedField": true,
                    "addHiddenField": true,
                    "addStarttimeEndtimeFields": false,
                    "aggregateRoot": false,
                    "categorizable": false,
                    "description": "",
                    "mapToTable": "",
                    "parentClass": "",
                    "sorting": false,
                    "type": "Entity",
                    "uid": "716043273420"
                },
                "propertyGroup": {
                    "properties": [
                        {
                            "allowedFileTypes": "",
                            "maxItems": "1",
                            "propertyDescription": "",
                            "propertyIsExcludeField": true,
                            "propertyIsRequired": false,
                            "propertyName": "name",
                            "propertyType": "String",
                            "uid": "242085263102"
                        },
                        {
                            "allowedFileTypes": "",
                            "maxItems": "1",
                            "propertyDescription": "",
                            "propertyIsExcludeField": true,
                            "propertyIsRequired": false,
                            "propertyName": "prename",
                            "propertyType": "String",
                            "uid": "666596626855"
                        },
                        {
                            "allowedFileTypes": "",
                            "maxItems": "1",
                            "propertyDescription": "",
                            "propertyIsExcludeField": true,
                            "propertyIsRequired": false,
                            "propertyName": "surname",
                            "propertyType": "String",
                            "uid": "14802914174"
                        }
                    ]
                },
                "relationGroup": {
                    "relations": []
                }
            }
        },
        {
            "config": {
                "position": [
                    48,
                    206
                ]
            },
            "name": "New Model Object",
            "value": {
                "actionGroup": {
                    "_default0_list": false,
                    "_default1_show": false,
                    "_default2_new_create": false,
                    "_default3_edit_update": false,
                    "_default4_delete": false,
                    "customActions": []
                },
                "name": "Informationstype",
                "objectsettings": {
                    "addDeletedField": true,
                    "addHiddenField": true,
                    "addStarttimeEndtimeFields": false,
                    "aggregateRoot": false,
                    "categorizable": false,
                    "description": "",
                    "mapToTable": "",
                    "parentClass": "",
                    "sorting": true,
                    "type": "Entity",
                    "uid": "1270745965393"
                },
                "propertyGroup": {
                    "properties": [
                        {
                            "allowedFileTypes": "",
                            "maxItems": "1",
                            "propertyDescription": "",
                            "propertyIsExcludeField": true,
                            "propertyIsRequired": false,
                            "propertyName": "informationstype",
                            "propertyType": "String",
                            "uid": "176413612946"
                        },
                        {
                            "allowedFileTypes": "",
                            "maxItems": "1",
                            "propertyDescription": "",
                            "propertyIsExcludeField": true,
                            "propertyIsRequired": false,
                            "propertyName": "definition",
                            "propertyType": "Text",
                            "uid": "1447683591157"
                        },
                        {
                            "allowedFileTypes": "",
                            "maxItems": "1",
                            "propertyDescription": "",
                            "propertyIsExcludeField": true,
                            "propertyIsRequired": true,
                            "propertyName": "validity",
                            "propertyType": "Integer",
                            "uid": "706012668343"
                        },
                        {
                            "allowedFileTypes": "",
                            "maxItems": "1",
                            "propertyDescription": "",
                            "propertyIsExcludeField": true,
                            "propertyIsRequired": true,
                            "propertyName": "media",
                            "propertyType": "Integer",
                            "uid": "1104814971048"
                        }
                    ]
                },
                "relationGroup": {
                    "relations": []
                }
            }
        },
        {
            "config": {
                "position": [
                    526,
                    375
                ]
            },
            "name": "New Model Object",
            "value": {
                "actionGroup": {
                    "_default0_list": false,
                    "_default1_show": false,
                    "_default2_new_create": false,
                    "_default3_edit_update": false,
                    "_default4_delete": false,
                    "customActions": []
                },
                "name": "Canton",
                "objectsettings": {
                    "addDeletedField": true,
                    "addHiddenField": true,
                    "addStarttimeEndtimeFields": false,
                    "aggregateRoot": false,
                    "categorizable": false,
                    "description": "",
                    "mapToTable": "",
                    "parentClass": "",
                    "sorting": true,
                    "type": "Entity",
                    "uid": "1073548234468"
                },
                "propertyGroup": {
                    "properties": [
                        {
                            "allowedFileTypes": "",
                            "maxItems": "1",
                            "propertyDescription": "",
                            "propertyIsExcludeField": true,
                            "propertyIsRequired": true,
                            "propertyName": "definition",
                            "propertyType": "String",
                            "uid": "757253612204"
                        },
                        {
                            "allowedFileTypes": "",
                            "maxItems": "1",
                            "propertyDescription": "",
                            "propertyIsExcludeField": true,
                            "propertyIsRequired": true,
                            "propertyName": "short",
                            "propertyType": "String",
                            "uid": "1112802349406"
                        }
                    ]
                },
                "relationGroup": {
                    "relations": []
                }
            }
        },
        {
            "config": {
                "position": [
                    528,
                    202
                ]
            },
            "name": "New Model Object",
            "value": {
                "actionGroup": {
                    "_default0_list": false,
                    "_default1_show": false,
                    "_default2_new_create": false,
                    "_default3_edit_update": false,
                    "_default4_delete": false,
                    "customActions": []
                },
                "name": "Category",
                "objectsettings": {
                    "addDeletedField": true,
                    "addHiddenField": true,
                    "addStarttimeEndtimeFields": false,
                    "aggregateRoot": false,
                    "categorizable": false,
                    "description": "",
                    "mapToTable": "",
                    "parentClass": "",
                    "sorting": true,
                    "type": "Entity",
                    "uid": "308056367654"
                },
                "propertyGroup": {
                    "properties": [
                        {
                            "allowedFileTypes": "",
                            "maxItems": "1",
                            "propertyDescription": "",
                            "propertyIsExcludeField": true,
                            "propertyIsRequired": false,
                            "propertyName": "definition",
                            "propertyType": "String",
                            "uid": "865896798535"
                        },
                        {
                            "allowedFileTypes": "",
                            "maxItems": "1",
                            "propertyDescription": "",
                            "propertyIsExcludeField": true,
                            "propertyIsRequired": false,
                            "propertyName": "short",
                            "propertyType": "String",
                            "uid": "1404956477462"
                        },
                        {
                            "allowedFileTypes": "",
                            "maxItems": "1",
                            "propertyDescription": "",
                            "propertyIsExcludeField": true,
                            "propertyIsRequired": false,
                            "propertyName": "description",
                            "propertyType": "Text",
                            "uid": "280697468754"
                        }
                    ]
                },
                "relationGroup": {
                    "relations": []
                }
            }
        },
        {
            "config": {
                "position": [
                    282,
                    30
                ]
            },
            "name": "New Model Object",
            "value": {
                "actionGroup": {
                    "_default0_list": false,
                    "_default1_show": false,
                    "_default2_new_create": false,
                    "_default3_edit_update": false,
                    "_default4_delete": false,
                    "customActions": []
                },
                "name": "Country",
                "objectsettings": {
                    "addDeletedField": true,
                    "addHiddenField": true,
                    "addStarttimeEndtimeFields": false,
                    "aggregateRoot": false,
                    "categorizable": false,
                    "description": "",
                    "mapToTable": "",
                    "parentClass": "",
                    "sorting": true,
                    "type": "Entity",
                    "uid": "1148764801770"
                },
                "propertyGroup": {
                    "properties": [
                        {
                            "allowedFileTypes": "",
                            "maxItems": "1",
                            "propertyDescription": "",
                            "propertyIsExcludeField": true,
                            "propertyIsRequired": true,
                            "propertyName": "definition",
                            "propertyType": "String",
                            "uid": "1405634594771"
                        },
                        {
                            "allowedFileTypes": "",
                            "maxItems": "1",
                            "propertyDescription": "",
                            "propertyIsExcludeField": true,
                            "propertyIsRequired": true,
                            "propertyName": "short",
                            "propertyType": "String",
                            "uid": "804160204106"
                        }
                    ]
                },
                "relationGroup": {
                    "relations": []
                }
            }
        },
        {
            "config": {
                "position": [
                    43,
                    26
                ]
            },
            "name": "New Model Object",
            "value": {
                "actionGroup": {
                    "_default0_list": false,
                    "_default1_show": false,
                    "_default2_new_create": false,
                    "_default3_edit_update": false,
                    "_default4_delete": false,
                    "customActions": []
                },
                "name": "Media",
                "objectsettings": {
                    "addDeletedField": true,
                    "addHiddenField": true,
                    "addStarttimeEndtimeFields": false,
                    "aggregateRoot": false,
                    "categorizable": false,
                    "description": "",
                    "mapToTable": "",
                    "parentClass": "",
                    "sorting": true,
                    "type": "Entity",
                    "uid": "469650826491"
                },
                "propertyGroup": {
                    "properties": [
                        {
                            "allowedFileTypes": "",
                            "maxItems": "1",
                            "propertyDescription": "",
                            "propertyIsExcludeField": true,
                            "propertyIsRequired": true,
                            "propertyName": "medium",
                            "propertyType": "String",
                            "uid": "166990362136"
                        }
                    ]
                },
                "relationGroup": {
                    "relations": [
                        {
                            "foreignRelationClass": "",
                            "lazyLoading": false,
                            "propertyIsExcludeField": true,
                            "relationDescription": "",
                            "relationName": "idInformationstype",
                            "relationType": "manyToMany",
                            "relationWire": "[wired]",
                            "uid": "713624615563"
                        }
                    ]
                }
            }
        },
        {
            "config": {
                "position": [
                    41,
                    370
                ]
            },
            "name": "New Model Object",
            "value": {
                "actionGroup": {
                    "_default0_list": false,
                    "_default1_show": false,
                    "_default2_new_create": false,
                    "_default3_edit_update": false,
                    "_default4_delete": false,
                    "customActions": []
                },
                "name": "Periodicals",
                "objectsettings": {
                    "addDeletedField": true,
                    "addHiddenField": true,
                    "addStarttimeEndtimeFields": false,
                    "aggregateRoot": false,
                    "categorizable": false,
                    "description": "",
                    "mapToTable": "",
                    "parentClass": "",
                    "sorting": true,
                    "type": "Entity",
                    "uid": "474516679701"
                },
                "propertyGroup": {
                    "properties": [
                        {
                            "allowedFileTypes": "",
                            "maxItems": "1",
                            "propertyDescription": "",
                            "propertyIsExcludeField": true,
                            "propertyIsRequired": false,
                            "propertyName": "name",
                            "propertyType": "String",
                            "uid": "1188333349377"
                        },
                        {
                            "allowedFileTypes": "",
                            "maxItems": "1",
                            "propertyDescription": "",
                            "propertyIsExcludeField": true,
                            "propertyIsRequired": true,
                            "propertyName": "short",
                            "propertyType": "String",
                            "uid": "285476709030"
                        },
                        {
                            "allowedFileTypes": "",
                            "maxItems": "1",
                            "propertyDescription": "",
                            "propertyIsExcludeField": true,
                            "propertyIsRequired": true,
                            "propertyName": "www",
                            "propertyType": "String",
                            "uid": "137072904341"
                        }
                    ]
                },
                "relationGroup": {
                    "relations": [
                        {
                            "foreignRelationClass": "",
                            "lazyLoading": false,
                            "propertyIsExcludeField": true,
                            "relationDescription": "",
                            "relationName": "idAdresse",
                            "relationType": "manyToOne",
                            "relationWire": "[wired]",
                            "uid": "996928952748"
                        }
                    ]
                }
            }
        },
        {
            "config": {
                "position": [
                    284,
                    210
                ]
            },
            "name": "New Model Object",
            "value": {
                "actionGroup": {
                    "_default0_list": false,
                    "_default1_show": false,
                    "_default2_new_create": false,
                    "_default3_edit_update": false,
                    "_default4_delete": false,
                    "customActions": []
                },
                "name": "Publisher",
                "objectsettings": {
                    "addDeletedField": true,
                    "addHiddenField": true,
                    "addStarttimeEndtimeFields": false,
                    "aggregateRoot": false,
                    "categorizable": false,
                    "description": "",
                    "mapToTable": "",
                    "parentClass": "",
                    "sorting": true,
                    "type": "Entity",
                    "uid": "1050423621873"
                },
                "propertyGroup": {
                    "properties": [
                        {
                            "allowedFileTypes": "",
                            "maxItems": "1",
                            "propertyDescription": "",
                            "propertyIsExcludeField": true,
                            "propertyIsRequired": false,
                            "propertyName": "publisher",
                            "propertyType": "Text",
                            "uid": "500866386914"
                        }
                    ]
                },
                "relationGroup": {
                    "relations": []
                }
            }
        },
        {
            "config": {
                "position": [
                    911,
                    363
                ]
            },
            "name": "New Model Object",
            "value": {
                "actionGroup": {
                    "_default0_list": false,
                    "_default1_show": false,
                    "_default2_new_create": false,
                    "_default3_edit_update": false,
                    "_default4_delete": false,
                    "customActions": []
                },
                "name": "Education",
                "objectsettings": {
                    "addDeletedField": true,
                    "addHiddenField": true,
                    "addStarttimeEndtimeFields": false,
                    "aggregateRoot": false,
                    "categorizable": false,
                    "description": "",
                    "mapToTable": "",
                    "parentClass": "",
                    "sorting": true,
                    "type": "Entity",
                    "uid": "1219543716700"
                },
                "propertyGroup": {
                    "properties": [
                        {
                            "allowedFileTypes": "",
                            "maxItems": "1",
                            "propertyDescription": "",
                            "propertyIsExcludeField": true,
                            "propertyIsRequired": true,
                            "propertyName": "title",
                            "propertyType": "String",
                            "uid": "990219716683"
                        },
                        {
                            "allowedFileTypes": "",
                            "maxItems": "1",
                            "propertyDescription": "",
                            "propertyIsExcludeField": true,
                            "propertyIsRequired": true,
                            "propertyName": "link",
                            "propertyType": "String",
                            "uid": "1146858998302"
                        }
                    ]
                },
                "relationGroup": {
                    "relations": [
                        {
                            "foreignRelationClass": "",
                            "lazyLoading": false,
                            "propertyIsExcludeField": true,
                            "relationDescription": "",
                            "relationName": "idEducationLevel",
                            "relationType": "manyToOne",
                            "relationWire": "[wired]",
                            "uid": "1076889377845"
                        }
                    ]
                }
            }
        },
        {
            "config": {
                "position": [
                    1253,
                    228
                ]
            },
            "name": "New Model Object",
            "value": {
                "actionGroup": {
                    "_default0_list": false,
                    "_default1_show": false,
                    "_default2_new_create": false,
                    "_default3_edit_update": false,
                    "_default4_delete": false,
                    "customActions": []
                },
                "name": "Range",
                "objectsettings": {
                    "addDeletedField": true,
                    "addHiddenField": true,
                    "addStarttimeEndtimeFields": false,
                    "aggregateRoot": false,
                    "categorizable": false,
                    "description": "",
                    "mapToTable": "",
                    "parentClass": "",
                    "sorting": true,
                    "type": "Entity",
                    "uid": "1066677846233"
                },
                "propertyGroup": {
                    "properties": [
                        {
                            "allowedFileTypes": "",
                            "maxItems": "1",
                            "propertyDescription": "",
                            "propertyIsExcludeField": true,
                            "propertyIsRequired": true,
                            "propertyName": "title",
                            "propertyType": "String",
                            "uid": "1287020035682"
                        },
                        {
                            "allowedFileTypes": "",
                            "maxItems": "1",
                            "propertyDescription": "",
                            "propertyIsExcludeField": true,
                            "propertyIsRequired": false,
                            "propertyName": "description",
                            "propertyType": "Text",
                            "uid": "631718178570"
                        }
                    ]
                },
                "relationGroup": {
                    "relations": []
                }
            }
        },
        {
            "config": {
                "position": [
                    1251,
                    383
                ]
            },
            "name": "New Model Object",
            "value": {
                "actionGroup": {
                    "_default0_list": false,
                    "_default1_show": false,
                    "_default2_new_create": false,
                    "_default3_edit_update": false,
                    "_default4_delete": false,
                    "customActions": []
                },
                "name": "EdcuationLevel",
                "objectsettings": {
                    "addDeletedField": true,
                    "addHiddenField": true,
                    "addStarttimeEndtimeFields": false,
                    "aggregateRoot": false,
                    "categorizable": false,
                    "description": "",
                    "mapToTable": "",
                    "parentClass": "",
                    "sorting": true,
                    "type": "Entity",
                    "uid": "1330330145531"
                },
                "propertyGroup": {
                    "properties": [
                        {
                            "allowedFileTypes": "",
                            "maxItems": "1",
                            "propertyDescription": "",
                            "propertyIsExcludeField": true,
                            "propertyIsRequired": true,
                            "propertyName": "title",
                            "propertyType": "String",
                            "uid": "1326771661757"
                        },
                        {
                            "allowedFileTypes": "",
                            "maxItems": "1",
                            "propertyDescription": "",
                            "propertyIsExcludeField": true,
                            "propertyIsRequired": true,
                            "propertyName": "level",
                            "propertyType": "Integer",
                            "uid": "570258449638"
                        }
                    ]
                },
                "relationGroup": {
                    "relations": []
                }
            }
        },
        {
            "config": {
                "position": [
                    972,
                    56
                ]
            },
            "name": "New Model Object",
            "value": {
                "actionGroup": {
                    "_default0_list": false,
                    "_default1_show": false,
                    "_default2_new_create": false,
                    "_default3_edit_update": false,
                    "_default4_delete": false,
                    "customActions": []
                },
                "name": "Offer",
                "objectsettings": {
                    "addDeletedField": true,
                    "addHiddenField": true,
                    "addStarttimeEndtimeFields": true,
                    "aggregateRoot": false,
                    "categorizable": false,
                    "description": "",
                    "mapToTable": "",
                    "parentClass": "",
                    "sorting": true,
                    "type": "Entity",
                    "uid": "207838488127"
                },
                "propertyGroup": {
                    "properties": [
                        {
                            "allowedFileTypes": "",
                            "maxItems": "1",
                            "propertyDescription": "",
                            "propertyIsExcludeField": true,
                            "propertyIsRequired": true,
                            "propertyName": "fegroup",
                            "propertyType": "Integer",
                            "uid": "32399959767"
                        },
                        {
                            "allowedFileTypes": "",
                            "maxItems": "1",
                            "propertyDescription": "",
                            "propertyIsExcludeField": true,
                            "propertyIsRequired": true,
                            "propertyName": "offerType",
                            "propertyType": "Integer",
                            "uid": "431804526820"
                        },
                        {
                            "allowedFileTypes": "",
                            "maxItems": "1",
                            "propertyDescription": "",
                            "propertyIsExcludeField": true,
                            "propertyIsRequired": true,
                            "propertyName": "number",
                            "propertyType": "Integer",
                            "uid": "23718392397"
                        },
                        {
                            "allowedFileTypes": "",
                            "maxItems": "1",
                            "propertyDescription": "",
                            "propertyIsExcludeField": true,
                            "propertyIsRequired": true,
                            "propertyName": "date",
                            "propertyType": "Integer",
                            "uid": "661941507321"
                        },
                        {
                            "allowedFileTypes": "",
                            "maxItems": "1",
                            "propertyDescription": "",
                            "propertyIsExcludeField": true,
                            "propertyIsRequired": true,
                            "propertyName": "location",
                            "propertyType": "String",
                            "uid": "1334801854511"
                        },
                        {
                            "allowedFileTypes": "",
                            "maxItems": "1",
                            "propertyDescription": "",
                            "propertyIsExcludeField": true,
                            "propertyIsRequired": true,
                            "propertyName": "title",
                            "propertyType": "String",
                            "uid": "1252147605246"
                        },
                        {
                            "allowedFileTypes": "",
                            "maxItems": "1",
                            "propertyDescription": "",
                            "propertyIsExcludeField": true,
                            "propertyIsRequired": false,
                            "propertyName": "content",
                            "propertyType": "Text",
                            "uid": "772772334308"
                        },
                        {
                            "allowedFileTypes": "",
                            "maxItems": "1",
                            "propertyDescription": "",
                            "propertyIsExcludeField": true,
                            "propertyIsRequired": false,
                            "propertyName": "infos",
                            "propertyType": "Text",
                            "uid": "809158131789"
                        },
                        {
                            "allowedFileTypes": "",
                            "maxItems": "1",
                            "propertyDescription": "",
                            "propertyIsExcludeField": true,
                            "propertyIsRequired": false,
                            "propertyName": "www",
                            "propertyType": "Text",
                            "uid": "300380696926"
                        },
                        {
                            "allowedFileTypes": "",
                            "maxItems": "1",
                            "propertyDescription": "",
                            "propertyIsExcludeField": true,
                            "propertyIsRequired": false,
                            "propertyName": "delDate",
                            "propertyType": "Integer",
                            "uid": "168240379457"
                        }
                    ]
                },
                "relationGroup": {
                    "relations": [
                        {
                            "foreignRelationClass": "",
                            "lazyLoading": true,
                            "propertyIsExcludeField": true,
                            "relationDescription": "",
                            "relationName": "idCategory",
                            "relationType": "manyToMany",
                            "relationWire": "[wired]",
                            "uid": "132794671156"
                        },
                        {
                            "foreignRelationClass": "",
                            "lazyLoading": false,
                            "propertyIsExcludeField": true,
                            "relationDescription": "",
                            "relationName": "idUser",
                            "relationType": "manyToOne",
                            "relationWire": "[wired]",
                            "uid": "135649369493"
                        },
                        {
                            "foreignRelationClass": "",
                            "lazyLoading": false,
                            "propertyIsExcludeField": true,
                            "relationDescription": "",
                            "relationName": "idDegree",
                            "relationType": "manyToOne",
                            "relationWire": "[wired]",
                            "uid": "413962764357"
                        }
                    ]
                }
            }
        },
        {
            "config": {
                "position": [
                    1251,
                    71
                ]
            },
            "name": "New Model Object",
            "value": {
                "actionGroup": {
                    "_default0_list": false,
                    "_default1_show": false,
                    "_default2_new_create": false,
                    "_default3_edit_update": false,
                    "_default4_delete": false,
                    "customActions": []
                },
                "name": "Degree",
                "objectsettings": {
                    "addDeletedField": true,
                    "addHiddenField": true,
                    "addStarttimeEndtimeFields": true,
                    "aggregateRoot": false,
                    "categorizable": false,
                    "description": "",
                    "mapToTable": "",
                    "parentClass": "",
                    "sorting": true,
                    "type": "Entity",
                    "uid": "1364904193040"
                },
                "propertyGroup": {
                    "properties": [
                        {
                            "allowedFileTypes": "",
                            "maxItems": "1",
                            "propertyDescription": "",
                            "propertyIsExcludeField": true,
                            "propertyIsRequired": true,
                            "propertyName": "title",
                            "propertyType": "String",
                            "uid": "1434517091017"
                        }
                    ]
                },
                "relationGroup": {
                    "relations": []
                }
            }
        },
        {
            "config": {
                "position": [
                    272,
                    383
                ]
            },
            "name": "New Model Object",
            "value": {
                "actionGroup": {
                    "_default0_list": false,
                    "_default1_show": false,
                    "_default2_new_create": false,
                    "_default3_edit_update": false,
                    "_default4_delete": false,
                    "customActions": []
                },
                "name": "AreasOfWork",
                "objectsettings": {
                    "addDeletedField": true,
                    "addHiddenField": true,
                    "addStarttimeEndtimeFields": false,
                    "aggregateRoot": false,
                    "categorizable": false,
                    "description": "",
                    "mapToTable": "",
                    "parentClass": "",
                    "sorting": true,
                    "type": "Entity",
                    "uid": "751474457797"
                },
                "propertyGroup": {
                    "properties": [
                        {
                            "allowedFileTypes": "",
                            "maxItems": "1",
                            "propertyDescription": "",
                            "propertyIsExcludeField": true,
                            "propertyIsRequired": true,
                            "propertyName": "description",
                            "propertyType": "String",
                            "uid": "896489277373"
                        },
                        {
                            "allowedFileTypes": "",
                            "maxItems": "1",
                            "propertyDescription": "",
                            "propertyIsExcludeField": true,
                            "propertyIsRequired": true,
                            "propertyName": "offer",
                            "propertyType": "Boolean",
                            "uid": "1246864782506"
                        },
                        {
                            "allowedFileTypes": "",
                            "maxItems": "1",
                            "propertyDescription": "",
                            "propertyIsExcludeField": true,
                            "propertyIsRequired": true,
                            "propertyName": "request",
                            "propertyType": "Boolean",
                            "uid": "1410647243167"
                        }
                    ]
                },
                "relationGroup": {
                    "relations": []
                }
            }
        },
        {
            "config": {
                "position": [
                    1046,
                    626
                ]
            },
            "name": "New Model Object",
            "value": {
                "actionGroup": {
                    "_default0_list": false,
                    "_default1_show": false,
                    "_default2_new_create": false,
                    "_default3_edit_update": false,
                    "_default4_delete": false,
                    "customActions": []
                },
                "name": "FeUser",
                "objectsettings": {
                    "addDeletedField": true,
                    "addHiddenField": true,
                    "addStarttimeEndtimeFields": true,
                    "aggregateRoot": false,
                    "categorizable": false,
                    "description": "",
                    "mapToTable": "",
                    "parentClass": "\\TYPO3\\CMS\\Extbase\\Domain\\Model\\FrontendUser",
                    "sorting": false,
                    "type": "Entity",
                    "uid": "632524848544"
                },
                "propertyGroup": {
                    "properties": []
                },
                "relationGroup": {
                    "relations": []
                }
            }
        }
    ],
    "properties": {
        "backendModules": [],
        "description": "",
        "emConf": {
            "category": "plugin",
            "custom_category": "",
            "dependsOn": "typo3 => 7.6.0-7.6.99\n",
            "disableLocalization": false,
            "disableVersioning": false,
            "skipGenerateDocumentationTemplate": false,
            "sourceLanguage": "en",
            "state": "alpha",
            "targetVersion": "7.6.0-7.6.99",
            "version": ""
        },
        "extensionKey": "si_news",
        "name": "Si News",
        "originalExtensionKey": "si_news",
        "originalVendorName": "Sozialinfo",
        "persons": [
            {
                "company": "Sozialinfo",
                "email": "pera91@mykolab.ch",
                "name": "Pera",
                "role": "Developer"
            }
        ],
        "plugins": [],
        "vendorName": "Sozialinfo"
    },
    "wires": [
        {
            "src": {
                "moduleId": 0,
                "terminal": "relationWire_0",
                "uid": "432031968945"
            },
            "tgt": {
                "moduleId": 2,
                "terminal": "SOURCES",
                "uid": "716043273420"
            }
        },
        {
            "src": {
                "moduleId": 0,
                "terminal": "relationWire_1",
                "uid": "393915008928"
            },
            "tgt": {
                "moduleId": 9,
                "terminal": "SOURCES",
                "uid": "1050423621873"
            }
        },
        {
            "src": {
                "moduleId": 0,
                "terminal": "relationWire_5",
                "uid": "1414041246328"
            },
            "tgt": {
                "moduleId": 5,
                "terminal": "SOURCES",
                "uid": "308056367654"
            }
        },
        {
            "src": {
                "moduleId": 0,
                "terminal": "relationWire_4",
                "uid": "308477501729"
            },
            "tgt": {
                "moduleId": 3,
                "terminal": "SOURCES",
                "uid": "1270745965393"
            }
        },
        {
            "src": {
                "moduleId": 0,
                "terminal": "relationWire_3",
                "uid": "1367924202115"
            },
            "tgt": {
                "moduleId": 1,
                "terminal": "SOURCES",
                "uid": "167147602477"
            }
        },
        {
            "src": {
                "moduleId": 0,
                "terminal": "relationWire_2",
                "uid": "934677918302"
            },
            "tgt": {
                "moduleId": 4,
                "terminal": "SOURCES",
                "uid": "1073548234468"
            }
        },
        {
            "src": {
                "moduleId": 1,
                "terminal": "relationWire_0",
                "uid": "574745817357"
            },
            "tgt": {
                "moduleId": 16,
                "terminal": "SOURCES",
                "uid": "632524848544"
            }
        },
        {
            "src": {
                "moduleId": 1,
                "terminal": "relationWire_1",
                "uid": "837849782902"
            },
            "tgt": {
                "moduleId": 4,
                "terminal": "SOURCES",
                "uid": "1073548234468"
            }
        },
        {
            "src": {
                "moduleId": 1,
                "terminal": "relationWire_2",
                "uid": "1044861095050"
            },
            "tgt": {
                "moduleId": 15,
                "terminal": "SOURCES",
                "uid": "751474457797"
            }
        },
        {
            "src": {
                "moduleId": 1,
                "terminal": "relationWire_3",
                "uid": "657861267026"
            },
            "tgt": {
                "moduleId": 10,
                "terminal": "SOURCES",
                "uid": "1219543716700"
            }
        },
        {
            "src": {
                "moduleId": 7,
                "terminal": "relationWire_0",
                "uid": "713624615563"
            },
            "tgt": {
                "moduleId": 3,
                "terminal": "SOURCES",
                "uid": "1270745965393"
            }
        },
        {
            "src": {
                "moduleId": 8,
                "terminal": "relationWire_0",
                "uid": "996928952748"
            },
            "tgt": {
                "moduleId": 1,
                "terminal": "SOURCES",
                "uid": "167147602477"
            }
        },
        {
            "src": {
                "moduleId": 13,
                "terminal": "relationWire_2",
                "uid": "413962764357"
            },
            "tgt": {
                "moduleId": 14,
                "terminal": "SOURCES",
                "uid": "1364904193040"
            }
        },
        {
            "src": {
                "moduleId": 10,
                "terminal": "relationWire_0",
                "uid": "1076889377845"
            },
            "tgt": {
                "moduleId": 12,
                "terminal": "SOURCES",
                "uid": "1330330145531"
            }
        },
        {
            "src": {
                "moduleId": 13,
                "terminal": "relationWire_1",
                "uid": "135649369493"
            },
            "tgt": {
                "moduleId": 16,
                "terminal": "SOURCES",
                "uid": "632524848544"
            }
        },
        {
            "src": {
                "moduleId": 13,
                "terminal": "relationWire_0",
                "uid": "132794671156"
            },
            "tgt": {
                "moduleId": 5,
                "terminal": "SOURCES",
                "uid": "308056367654"
            }
        }
    ],
    "log": {
        "last_modified": "2016-01-04 10:47",
        "extension_builder_version": "7.6.0",
        "be_user": " (1)"
    }
}